{
  "gitSyncId": "68f73f5b76976230880d2d60_0aff661b-7fba-4e11-aae3-fc7e90d34fa6",
  "id": "js_apiA360_js_apiA360",
  "isPublic": true,
  "unpublishedCollection": {
    "contextType": "MODULE",
    "moduleId": "js_apiA360",
    "name": "js_apiA360",
    "pluginId": "js-plugin",
    "pluginType": "JS",
    "variables": [
      {
        "name": "config",
        "value": "{\n  token: \"\",\n  username: {},\n  apikey: {},\n  runner: \"\",\n  maxTries: 20,\n  pollUnattended: 5000,\n  pollHeadless: 1500\n}"
      }
    ]
  }
}